py2gds/__init__.py
py2gds/algorithm.py
py2gds/collection.py
py2gds/connection.py
py2gds/dsl.py
py2gds/exceptions.py
py2gds/projection.py
py2gds/queries.py
py2gds/query.py
py2gds/rank.py
py2gds/utils.py
py2gds-0.1.2.dist-info/LICENSE
py2gds-0.1.2.dist-info/WHEEL
py2gds-0.1.2.dist-info/METADATA
py2gds-0.1.2.dist-info/RECORD
