Metadata-Version: 2.1
Name: py2gds
Version: 0.1.2
Summary: Library to build Neo4j queries with special attention on Graph Data Science library calls.
License: MIT
Author: Pablo Cabezas
Author-email: pabcabsal@gmail.com
Requires-Python: >=3.8,<4.0
Classifier: License :: OSI Approved :: MIT License
Classifier: Programming Language :: Python :: 3
Classifier: Programming Language :: Python :: 3.8
Requires-Dist: neo4j (>=4.2,<5.0)
